aiverify_shap_toolbox/__init__.py
aiverify_shap_toolbox/__main__.py
aiverify_shap_toolbox/algo.meta.json
aiverify_shap_toolbox/algo.py
aiverify_shap_toolbox/algo_init.py
aiverify_shap_toolbox/input.schema.json
aiverify_shap_toolbox/output.schema.json
aiverify_shap_toolbox/plugin_init.py
aiverify_shap_toolbox/utils/__init__.py
aiverify_shap_toolbox/utils/algo_types.py
aiverify_shap_toolbox/utils/explain_types.py
aiverify_shap_toolbox-2.1.0.dist-info/METADATA
aiverify_shap_toolbox-2.1.0.dist-info/WHEEL
aiverify_shap_toolbox-2.1.0.dist-info/entry_points.txt
aiverify_shap_toolbox-2.1.0.dist-info/licenses/AUTHORS.rst
aiverify_shap_toolbox-2.1.0.dist-info/licenses/LICENSE
aiverify_shap_toolbox-2.1.0.dist-info/licenses/NOTICE.md
aiverify_shap_toolbox-2.1.0.dist-info/RECORD
