Metadata-Version: 2.4
Name: aiverify-shap-toolbox
Version: 2.1.0
Summary: AI Verify SHAP Toolbox provides SHAP (SHapley Additive exPlanations) methods to explain the output of machine learning models.
Author: AI Verify
License-File: AUTHORS.rst
License-File: LICENSE
License-File: NOTICE.md
Requires-Python: <3.13,>=3.10
Requires-Dist: aiverify-test-engine>=2.1.0
Requires-Dist: joblib==1.4.2
Requires-Dist: numpy==1.26.4
Requires-Dist: pandas==2.2.2
Requires-Dist: scikit-learn==1.5.2
Requires-Dist: scipy==1.14.1
Requires-Dist: shap==0.46.0
Requires-Dist: xgboost==2.1.1
